README.md
setup.py
uint/__init__.py
uint/int.py
uint/register.py
uint/test_int.py
uint/test_register.py
uint/test_uint.py
uint/uint.py
uint/util.py
uint.egg-info/PKG-INFO
uint.egg-info/SOURCES.txt
uint.egg-info/dependency_links.txt
uint.egg-info/top_level.txt